processwebpagepkg/__init__.py
processwebpagepkg/processwebpage.py
processwebpage-0.0.2.dist-info/METADATA
processwebpage-0.0.2.dist-info/WHEEL
processwebpage-0.0.2.dist-info/licenses/LICENSE
processwebpage-0.0.2.dist-info/RECORD
